multirepo.py
setup.py
multirepo.egg-info/PKG-INFO
multirepo.egg-info/SOURCES.txt
multirepo.egg-info/dependency_links.txt
multirepo.egg-info/top_level.txt
multirepo.egg-info/zip-safe