Metadata-Version: 1.0
Name: multirepo
Version: 1.0rc2
Summary: Mercurial extension to affect multiple repositories simultaneously.
Home-page: http://bitbucket.org/ilowe/multirepo
Author: Iain Lowe
Author-email: iain.lowe@gmail.com
License: MIT
Download-URL: http://bitbucket.org/ilowe/multirepo/downloads
Keywords: hg scm mercurial multirepo multiple
Platform: UNKNOWN
